setup.py
Flask_Config_Helper.egg-info/PKG-INFO
Flask_Config_Helper.egg-info/SOURCES.txt
Flask_Config_Helper.egg-info/dependency_links.txt
Flask_Config_Helper.egg-info/not-zip-safe
Flask_Config_Helper.egg-info/requires.txt
Flask_Config_Helper.egg-info/top_level.txt
flask_config_helper/__init__.py