Metadata-Version: 1.1
Name: Flask-Config-Helper
Version: 0.1.1
Summary: Flask configuration helper
Home-page: http://github.com/yoophi/flask-config-helper/
Author: Pyunghyuk Yoo
Author-email: yoophi@gmail.com
License: MIT License
Platform: any
Classifier: Environment :: Web Environment
Classifier: Intended Audience :: Developers
Classifier: License :: OSI Approved :: MIT License
Classifier: Operating System :: OS Independent
Classifier: Programming Language :: Python
Classifier: Topic :: Software Development :: Libraries :: Python Modules
